llm_plugin_generator/__init__.py
llm_plugin_generator/few_shot_prompt_llm_plugin_all.xml
llm_plugin_generator/few_shot_prompt_llm_plugin_model.xml
llm_plugin_generator/few_shot_prompt_llm_plugin_utility.xml
llm_plugin_generator-0.5.dist-info/LICENSE
llm_plugin_generator-0.5.dist-info/METADATA
llm_plugin_generator-0.5.dist-info/WHEEL
llm_plugin_generator-0.5.dist-info/entry_points.txt
llm_plugin_generator-0.5.dist-info/top_level.txt
llm_plugin_generator-0.5.dist-info/RECORD
