Metadata-Version: 2.1
Name: llm-plugin-generator
Version: 0.5
Summary: LLM plugin to generate few-shot prompts for plugin creation
Author: llm-plugin-generator
License: Apache-2.0
Project-URL: Homepage, https://github.com/irthomasthomas/llm-plugin-generator
Project-URL: Changelog, https://github.com/irthomasthomas/llm-plugin-generator/releases
Project-URL: Issues, https://github.com/irthomasthomas/llm-plugin-generator/issues
Classifier: License :: OSI Approved :: Apache Software License
License-File: LICENSE
Requires-Dist: llm
Requires-Dist: click
Requires-Dist: gitpython
Provides-Extra: test
Requires-Dist: pytest ; extra == 'test'
